limen/__init__.py
limen/backtest/__init__.py
limen/backtest/backtest_sequential.py
limen/backtest/backtest_snapshot.py
limen/cohort/__init__.py
limen/cohort/regime_pools.py
limen/data/__init__.py
limen/data/historical_data.py
limen/data/_internal/binance_file_to_polars.py
limen/data/_internal/generic_endpoints.py
limen/data/bars/__init__.py
limen/data/bars/standard_bars.py
limen/data/utils/__init__.py
limen/data/utils/compute_data_bars.py
limen/data/utils/random_slice.py
limen/data/utils/splits.py
limen/experiment/__init__.py
limen/experiment/experiment_core.py
limen/experiment/manifest_core.py
limen/features/__init__.py
limen/features/active_lines.py
limen/features/active_quantile_count.py
limen/features/atr_percent_sma.py
limen/features/atr_sma.py
limen/features/breakout_features.py
limen/features/breakout_percentile_regime.py
limen/features/close_position.py
limen/features/close_to_extremes.py
limen/features/conserved_flux_renormalization.py
limen/features/distance_from_high.py
limen/features/distance_from_low.py
limen/features/dynamic_stop_loss.py
limen/features/dynamic_target.py
limen/features/ema_alignment.py
limen/features/ema_breakout.py
limen/features/entry_score_microstructure.py
limen/features/exit_quality.py
limen/features/feature_aliases.py
limen/features/forward_breakout_target.py
limen/features/gap_high.py
limen/features/hh_hl_structure_regime.py
limen/features/hours_since_big_move.py
limen/features/hours_since_quantile_line.py
limen/features/ichimoku_cloud.py
limen/features/kline_imbalance.py
limen/features/lagged_features.py
limen/features/log_returns.py
limen/features/ma_slope_regime.py
limen/features/market_regime.py
limen/features/micro_momentum.py
limen/features/momentum_confirmation.py
limen/features/momentum_periods.py
limen/features/momentum_weight.py
limen/features/position_in_candle.py
limen/features/position_in_range.py
limen/features/price_range_position.py
limen/features/price_vs_band_regime.py
limen/features/quantile_flag.py
vaquum_limen-1.32.0.dist-info/licenses/LICENSE
vaquum_limen-1.32.0.dist-info/METADATA
vaquum_limen-1.32.0.dist-info/WHEEL
vaquum_limen-1.32.0.dist-info/top_level.txt
vaquum_limen-1.32.0.dist-info/RECORD
