Metadata-Version: 2.4
Name: vaquum_limen
Version: 1.32.0
Summary: Bitcoin-first research and trading platform.
Author: Prasenjit Dey, Arun Raguraman, Jatin Thakur, Soujanyaa Boruah, Ng Wei Da
Author-email: Mikko Kotila <mailme@mikkokotila.com>
License: MIT
Project-URL: Homepage, https://vaquum.fi
Project-URL: Repository, https://github.com/vaquum/limen
Requires-Python: >=3.10
License-File: LICENSE
Requires-Dist: pandas>=2.3.1
Requires-Dist: polars>=1.0.0
Requires-Dist: scikit-learn>=1.6.1
Requires-Dist: tqdm>=4.67.0
Requires-Dist: xgboost
Requires-Dist: python-dotenv
Requires-Dist: scipy
Requires-Dist: tslearn
Requires-Dist: optuna
Requires-Dist: clickhouse_connect
Requires-Dist: lightgbm
Requires-Dist: wrangle
Requires-Dist: pyarrow
Requires-Dist: numpy>=2.2.6
Requires-Dist: matplotlib
Requires-Dist: seaborn
Requires-Dist: streamlit
Requires-Dist: plotly
Requires-Dist: ipython
Requires-Dist: mcp>=0.1.0
Requires-Dist: playwright
Provides-Extra: tabpfn
Requires-Dist: tabpfn>=6; extra == "tabpfn"
Dynamic: license-file
